llama_cpp/__init__.py
llama_cpp/convert_model.py
llama_cpp/deploy_windows.py
llama_cpp/install_conversion_libs.py
llama_cpp/binaries/llama-b6497-bin-win-cpu-x64.zip
llama_cpp_pydist-0.9.0.dist-info/licenses/LICENSE
vendor_llama_cpp_pydist/__init__.py
vendor_llama_cpp_pydist/llama.cpp/.clang-format
vendor_llama_cpp_pydist/llama.cpp/.clang-tidy
vendor_llama_cpp_pydist/llama.cpp/.dockerignore
vendor_llama_cpp_pydist/llama.cpp/.ecrc
vendor_llama_cpp_pydist/llama.cpp/.editorconfig
vendor_llama_cpp_pydist/llama.cpp/.flake8
vendor_llama_cpp_pydist/llama.cpp/.git
vendor_llama_cpp_pydist/llama.cpp/.gitignore
vendor_llama_cpp_pydist/llama.cpp/.gitmodules
vendor_llama_cpp_pydist/llama.cpp/.pre-commit-config.yaml
vendor_llama_cpp_pydist/llama.cpp/AUTHORS
vendor_llama_cpp_pydist/llama.cpp/CMakeLists.txt
vendor_llama_cpp_pydist/llama.cpp/CMakePresets.json
vendor_llama_cpp_pydist/llama.cpp/CODEOWNERS
vendor_llama_cpp_pydist/llama.cpp/CONTRIBUTING.md
vendor_llama_cpp_pydist/llama.cpp/LICENSE
vendor_llama_cpp_pydist/llama.cpp/Makefile
vendor_llama_cpp_pydist/llama.cpp/README.md
vendor_llama_cpp_pydist/llama.cpp/SECURITY.md
vendor_llama_cpp_pydist/llama.cpp/build-xcframework.sh
vendor_llama_cpp_pydist/llama.cpp/convert_hf_to_gguf.py
vendor_llama_cpp_pydist/llama.cpp/convert_hf_to_gguf_update.py
vendor_llama_cpp_pydist/llama.cpp/convert_llama_ggml_to_gguf.py
vendor_llama_cpp_pydist/llama.cpp/convert_lora_to_gguf.py
vendor_llama_cpp_pydist/llama.cpp/flake.lock
vendor_llama_cpp_pydist/llama.cpp/flake.nix
vendor_llama_cpp_pydist/llama.cpp/mypy.ini
vendor_llama_cpp_pydist/llama.cpp/poetry.lock
vendor_llama_cpp_pydist/llama.cpp/pyproject.toml
vendor_llama_cpp_pydist/llama.cpp/pyrightconfig.json
vendor_llama_cpp_pydist/llama.cpp/requirements.txt
vendor_llama_cpp_pydist/llama.cpp/.devops/cann.Dockerfile
vendor_llama_cpp_pydist/llama.cpp/.devops/cpu.Dockerfile
vendor_llama_cpp_pydist/llama.cpp/.devops/cuda.Dockerfile
vendor_llama_cpp_pydist/llama.cpp/.devops/intel.Dockerfile
llama_cpp_pydist-0.9.0.dist-info/METADATA
llama_cpp_pydist-0.9.0.dist-info/WHEEL
llama_cpp_pydist-0.9.0.dist-info/top_level.txt
llama_cpp_pydist-0.9.0.dist-info/RECORD
