Metadata-Version: 2.4
Name: llama_cpp_pydist
Version: 0.9.0
Summary: A Python package for Llama CPP.
Home-page: https://github.com/shamitv/llama_cpp
Author: Shamit Verma
Author-email: oss@shamit.in
Project-URL: Changelog, https://github.com/shamitv/llama_cpp/blob/main/CHANGELOG.md
Project-URL: Source, https://github.com/shamitv/llama_cpp
Project-URL: Issues, https://github.com/shamitv/llama_cpp/issues
Classifier: Programming Language :: Python :: 3
Classifier: License :: OSI Approved :: Apache Software License
Classifier: Development Status :: 5 - Production/Stable
Classifier: Intended Audience :: Developers
Classifier: Operating System :: OS Independent
Requires-Python: >=3.9
License-File: LICENSE
Dynamic: author
Dynamic: author-email
Dynamic: classifier
Dynamic: description
Dynamic: description-content-type
Dynamic: home-page
Dynamic: license-file
Dynamic: project-url
Dynamic: requires-python
Dynamic: summary
